{
  "title": "Kubernetes: Deploy and open the Dashboard",
  "description": "Intermediate: Install the web UI on a training cluster and sign in with a token (lab-only security settings).",
  "details": {
    "difficulty": "Intermediate",
    "intro": {
      "text": "intro.md"
    },
    "steps": [
      {
        "title": "Deploy Dashboard and sign in",
        "text": "step1/text.md",
        "verify": "step1/verify.sh"
      }
    ],
    "finish": {
      "text": "finish.md"
    },
    "assets": {
      "host01": [
        {"file": "dashboard.yaml", "target": "/root", "chmod": "+w"}
      ]
    }
  },
  "backend": {
    "imageid": "kubernetes-kubeadm-1node"
  }
}
